rio_alpha/__init__.py
rio_alpha/alpha.py
rio_alpha/alpha_mask.py
rio_alpha/findnodata.py
rio_alpha/islossy.py
rio_alpha/utils.py
rio_alpha/scripts/__init__.py
rio_alpha/scripts/cli.py
rio_alpha-1.0.2.dist-info/LICENSE.txt
rio_alpha-1.0.2.dist-info/METADATA
rio_alpha-1.0.2.dist-info/WHEEL
rio_alpha-1.0.2.dist-info/entry_points.txt
rio_alpha-1.0.2.dist-info/top_level.txt
rio_alpha-1.0.2.dist-info/RECORD
