Metadata-Version: 2.1
Name: rio-alpha
Version: 1.0.2
Summary: A replacement for pxm-alpha
Home-page: https://github.com/mapbox/rio-alpha
Author: Virginia Ng
Author-email: virginia@mapbox.com
License: BSD
Platform: UNKNOWN
License-File: LICENSE.txt
Requires-Dist: click (>=6)
Requires-Dist: rasterio (~=1.0)
Requires-Dist: rio-mucho (>=1.0rc1)
Requires-Dist: scipy (>=0.18)
Provides-Extra: plot
Requires-Dist: matplotlib ; extra == 'plot'
Provides-Extra: test
Requires-Dist: codecov ; extra == 'test'
Requires-Dist: hypothesis ; extra == 'test'
Requires-Dist: pytest ; extra == 'test'
Requires-Dist: pytest-cov ; extra == 'test'
